dkdc_vault/__init__.py
dkdc_vault/main.py
dkdc_vault-0.0.1.dist-info/METADATA
dkdc_vault-0.0.1.dist-info/WHEEL
dkdc_vault-0.0.1.dist-info/top_level.txt
dkdc_vault-0.0.1.dist-info/RECORD
